MANIFEST.in
README.md
pyproject.toml
requirements.txt
setup.py
jaison/__about__.py
jaison/__init__.py
jaison.egg-info/PKG-INFO
jaison.egg-info/SOURCES.txt
jaison.egg-info/dependency_links.txt
jaison.egg-info/requires.txt
jaison.egg-info/top_level.txt
jaison/analysis/__init__.py
jaison/analysis/acc_stats.py
jaison/analysis/explain.py
jaison/analysis/model_analyzer.py
jaison/analysis/nc/__init__.py
jaison/analysis/nc/base.py
jaison/analysis/nc/icp.py
jaison/analysis/nc/metrics.py
jaison/analysis/nc/nc.py
jaison/analysis/nc/norm.py
jaison/analysis/nc/util.py
jaison/analysis/nc/wrappers.py
jaison/api/__init__.py
jaison/api/dtype.py
jaison/api/encode.py
jaison/api/ensemble.py
jaison/api/high_level.py
jaison/api/json_ai.py
jaison/api/predictor.py
jaison/api/types.py
jaison/data/__init__.py
jaison/data/cleaner.py
jaison/data/encoded_ds.py
jaison/data/infer_types.py
jaison/data/splitter.py
jaison/data/statistical_analysis.py
jaison/data/timeseries_analyzer.py
jaison/data/timeseries_transform.py
jaison/encoder/__init__.py
jaison/encoder/base.py
jaison/encoder/audio/__init__.py
jaison/encoder/audio/amplitude_ts.py
jaison/encoder/categorical/__init__.py
jaison/encoder/categorical/autoencoder.py
jaison/encoder/categorical/binary.py
jaison/encoder/categorical/gym.py
jaison/encoder/categorical/multihot.py
jaison/encoder/categorical/onehot.py
jaison/encoder/datetime/__init__.py
jaison/encoder/datetime/datetime.py
jaison/encoder/image/__init__.py
jaison/encoder/image/img_2_vec.py
jaison/encoder/image/helpers/__init__.py
jaison/encoder/image/helpers/img_to_vec.py
jaison/encoder/numeric/__init__.py
jaison/encoder/numeric/numeric.py
jaison/encoder/numeric/ts_array_numeric.py
jaison/encoder/numeric/ts_numeric.py
jaison/encoder/text/__init__.py
jaison/encoder/text/pretrained.py
jaison/encoder/text/rnn.py
jaison/encoder/text/short.py
jaison/encoder/text/tfidf.py
jaison/encoder/text/vocab.py
jaison/encoder/text/helpers/__init__.py
jaison/encoder/text/helpers/pretrained_helpers.py
jaison/encoder/text/helpers/rnn_helpers.py
jaison/encoder/time_series/__init__.py
jaison/encoder/time_series/plain.py
jaison/encoder/time_series/rnn.py
