Metadata-Version: 2.1
Name: jaison
Version: 1.0.0
Summary: jaison is a toolkit for automatic machine learning model building
Home-page: https://github.com/mindsdb/jaison
Author: MindsDB Inc
Author-email: community@mindsdb.com
License: GPL-3.0
Download-URL: https://pypi.org/project/jaison
Platform: UNKNOWN
Classifier: Programming Language :: Python :: 3
Classifier: License :: OSI Approved :: MIT License
Classifier: Operating System :: OS Independent
Requires-Python: >=3.6
